{
  $schema: 'https://docs.renovatebot.com/renovate-schema.json',
  extends: [
    'config:recommended',
    'helpers:pinGitHubActionDigests',
    ':pinDevDependencies'
  ],
  packageRules: [
    // Auto merge
    {
      "description": "Auto merge GitHub Actions",
      "groupName": "github-actions",
      "matchDatasources": ["github-tags"],
      "matchUpdateTypes": ["minor", "patch", "digest", "pinDigest"],
      "automerge": true
    },
    // Containers
    {
      "matchDatasources": ["docker"],
      "matchUpdateTypes": ["digest", "pinDigest"],
      "commitMessagePrefix": "chore({{depName}}): ",
      "automerge": true
    },
    {
      "matchFileNames": ["containers/**"],
      "matchUpdateTypes": ["patch"],
      "commitMessagePrefix": "fix({{depName}}): "
    },
    {
      "matchFileNames": ["containers/**"],
      "matchUpdateTypes": ["minor"],
      "commitMessagePrefix": "feat({{depName}}): "
    },
    {
      "matchFileNames": ["containers/**"],
      "matchUpdateTypes": ["major"],
      "commitMessagePrefix": "feat!({{depName}}): "
    }
  ]
}
